[
    {
        "name": "NollyVerse",
        "results": {
            "popular": {
                "error": "java.io.IOException: eu.kanade.tachiyomi.network.interceptor.CFClearance$CloudflareBypassException",
                "passed": false
            },
            "latest": {
                "error": "java.io.IOException: eu.kanade.tachiyomi.network.interceptor.CFClearance$CloudflareBypassException",
                "passed": false
            },
            "search": {
                "error": "java.io.IOException: eu.kanade.tachiyomi.network.interceptor.CFClearance$CloudflareBypassException",
                "passed": false
            },
            "details": {
                "error": "java.io.IOException: eu.kanade.tachiyomi.network.interceptor.CFClearance$CloudflareBypassException",
                "passed": false
            },
            "episodes": {
                "error": "java.io.IOException: eu.kanade.tachiyomi.network.interceptor.CFClearance$CloudflareBypassException",
                "passed": false
            },
            "videos": {
                "error": "java.lang.NullPointerException",
                "passed": false
            }
        }
    }
]