[
    {
        "name": "AnimesOnline (PT-BR)",
        "results": {
            "popular": {
                "result": [
                    {
                        "animes": [
                            {
                                "url": "/animes/hametsu-no-oukoku/",
                                "title": "Hametsu no Oukoku",
                                "thumbnail_url": "https://image.tmdb.org/t/p/w92/j7W5SOtsx6giPtvubEXqWWzKxDL.jpg"
                            },
                            {
                                "url": "/animes/kikansha-no-mahou-wa-tokubetsu-desu/",
                                "title": "Kikansha no Mahou wa Tokubetsu desu",
                                "thumbnail_url": "https://image.tmdb.org/t/p/w92/sTrb9Fd7cuKA6CnQN8kTjk0Jibv.jpg"
                            },
                            {
                                "url": "/animes/masamune-kun-no-revenge-r/",
                                "title": "Masamune-kun no Revenge R",
                                "thumbnail_url": "https://image.tmdb.org/t/p/w92/4MHexcfvP4FeaInZ20ncvk5hds5.jpg"
                            },
                            {
                                "url": "/animes/mushoku-tensei-isekai-ittara-honki-dasu/",
                                "title": "Mushoku Tensei: Isekai Ittara Honki Dasu",
                                "thumbnail_url": "https://image.tmdb.org/t/p/w92/uOwjWZOJwddC5ZwIx0Wl7pNsLB9.jpg"
                            },
                            {
                                "url": "/animes/left-hand-layup/",
                                "title": "Left-Hand Layup!",
                                "thumbnail_url": "https://image.tmdb.org/t/p/w92/eONDt3A8fBeAaDMiqN5roullnJL.jpg"
                            },
                            {
                                "url": "/animes/potion-danomi-de-ikinobimasu/",
                                "title": "Potion-danomi de Ikinobimasu!",
                                "thumbnail_url": "https://image.tmdb.org/t/p/w92/hNTugrX83FZz0zMC0lLbq9L89ty.jpg"
                            },
                            {
                                "url": "/animes/dead-mount-death-play/",
                                "title": "Dead Mount Death Play",
                                "thumbnail_url": "https://image.tmdb.org/t/p/w92/rfpFibe2JIuFLGZ9WPTrNlAYQnA.jpg"
                            },
                            {
                                "url": "/animes/eiyuu-kyoushitsu-dublado/",
                                "title": "Eiyuu Kyoushitsu Dublado",
                                "thumbnail_url": "https://image.tmdb.org/t/p/w92/v6g67rHGQZ8HeCpYAaIRQ3VGp8j.jpg"
                            },
                            {
                                "url": "/animes/shangri-la-frontier/",
                                "title": "Shangri-La Frontier",
                                "thumbnail_url": "https://image.tmdb.org/t/p/w92/v9bl7yQduqMS7RBrUyzN7aUE34Q.jpg"
                            },
                            {
                                "url": "/animes/isekai-de-cheat-skill-wo-te-ni-shita-ore-wa-genjitsu-sekai-wo-mo-musou-suru-level-up-wa-jinsei-wo-kaeta/",
                                "title": "Isekai de Cheat Skill wo Te ni Shita Ore wa, Genjitsu Sekai wo mo Musou Suru: Level Up wa Jinsei wo Kaeta",
                                "thumbnail_url": "https://image.tmdb.org/t/p/w92/50OsbGp6AWw4za2aAM82vKburcg.jpg"
                            }
                        ],
                        "hasNextPage": false
                    }
                ],
                "passed": true
            },
            "latest": {
                "result": [
                    {
                        "animes": [
                            {
                                "url": "/episodio/boushoku-no-berserk-episodio-2/",
                                "title": "Boushoku no Berserk – Episódio 2",
                                "thumbnail_url": "https://image.tmdb.org/t/p/w500_and_h282_face/9ZMVS5c8wh0BsodbITjXXEMVc9.jpg"
                            },
                            {
                                "url": "/episodio/kimi-no-koto-ga-daidaidaidaidaisuki-na-100-nin-no-kanojo-episodio-1/",
                                "title": "Kimi no Koto ga Daidaidaidaidaisuki na 100-nin no Kanojo – Episódio 1",
                                "thumbnail_url": "https://image.tmdb.org/t/p/w500_and_h282_face/mwH7L5e5pfCDRkATCftHa4aO5WX.jpg"
                            },
                            {
                                "url": "/episodio/overtake-episodio-2/",
                                "title": "Overtake! – Episódio 2",
                                "thumbnail_url": "https://image.tmdb.org/t/p/w500_and_h282_face/svIt3CKdG7ZI6lRNhSIrsNvpUpb.jpg"
                            },
                            {
                                "url": "/episodio/dekoboko-majo-no-oyako-jijou-episodio-3/",
                                "title": "Dekoboko Majo no Oyako Jijou – Episódio 3",
                                "thumbnail_url": "https://image.tmdb.org/t/p/w500_and_h282_face/kM9azz6bTgxqr6y7O4BxiPXcObO.jpg"
                            },
                            {
                                "url": "/episodio/nanatsu-no-taizai-mokushiroku-no-yonkishi-episodio-1/",
                                "title": "Nanatsu no Taizai: Mokushiroku no Yonkishi – Episódio 1",
                                "thumbnail_url": "https://image.tmdb.org/t/p/w500_and_h282_face/rGqgOMCuYJEcPbHhZDGX2vMiAoG.jpg"
                            },
                            {
                                "url": "/episodio/shangri-la-frontier-episodio-2/",
                                "title": "Shangri-La Frontier – Episódio 2",
                                "thumbnail_url": "https://image.tmdb.org/t/p/w500_and_h282_face/8qU5suic2xgx54CscaQnEGJw0CU.jpg"
                            },
                            {
                                "url": "/episodio/undead-unluck-episodio-1/",
                                "title": "Undead Unluck – Episódio 1",
                                "thumbnail_url": "https://image.tmdb.org/t/p/w500_and_h282_face/qteEi87xkfjR2xVCh3vBw9DkJDW.jpg"
                            },
                            {
                                "url": "/episodio/bokura-no-ameiro-protocol-episodio-1/",
                                "title": "Bokura no Ameiro Protocol – Episódio 1",
                                "thumbnail_url": "https://image.tmdb.org/t/p/w500_and_h282_face/udfqP06bmeaZSO5hNDBGE1eq1yN.jpg"
                            },
                            {
                                "url": "/episodio/potion-danomi-de-ikinobimasu-episodio-1/",
                                "title": "Potion-danomi de Ikinobimasu! – Episódio 1",
                                "thumbnail_url": "https://image.tmdb.org/t/p/w500_and_h282_face/hG8HKlHcJ4qGv9zkktpsjlayPqx.jpg"
                            },
                            {
                                "url": "/episodio/buta-no-liver-wa-kanetsu-shiro-episodio-1/",
                                "title": "Buta no Liver wa Kanetsu Shiro – Episódio 1",
                                "thumbnail_url": "https://image.tmdb.org/t/p/w500_and_h282_face/enBt0HP1rhNTFarKLzj7F3oOVIh.jpg"
                            },
                            {
                                "url": "/episodio/kikansha-no-mahou-wa-tokubetsu-desu-episodio-1/",
                                "title": "Kikansha no Mahou wa Tokubetsu desu – Episódio 1",
                                "thumbnail_url": "https://image.tmdb.org/t/p/w500_and_h282_face/jcisuCfT49gxfSSUtMravLXWrWh.jpg"
                            },
                            {
                                "url": "/episodio/ragna-crimson-episodio-2/",
                                "title": "Ragna Crimson – Episódio 2",
                                "thumbnail_url": "https://image.tmdb.org/t/p/w500_and_h282_face/7ddLCgIThqhY7aC5I5ZlBgaxT3K.jpg"
                            },
                            {
                                "url": "/episodio/tearmoon-teikoku-monogatari-dantoudai-kara-hajimaru-hime-no-tensei-gyakuten-story-episodio-1/",
                                "title": "Tearmoon Teikoku Monogatari: Dantoudai kara Hajimaru, Hime no Tensei Gyakuten Story – Episódio 1",
                                "thumbnail_url": "https://image.tmdb.org/t/p/w500_and_h282_face/ywj9dAQZsF5EEBXtIfy7nqpqOi6.jpg"
                            },
                            {
                                "url": "/episodio/atarashii-joushi-wa-do-tennen-episodio-1/",
                                "title": "Atarashii Joushi wa Do Tennen – Episódio 1",
                                "thumbnail_url": "https://image.tmdb.org/t/p/w500_and_h282_face/8Ql0zbSr8tQfBsJhoVnv56Sm6cr.jpg"
                            },
                            {
                                "url": "/episodio/spy-x-family-2-episodio-1/",
                                "title": "Spy x Family 2 – Episódio 1",
                                "thumbnail_url": "https://image.tmdb.org/t/p/w500_and_h282_face/pMbkz7E1kJ2e8b5E8Q4qkiZqdv4.jpg"
                            },
                            {
                                "url": "/episodio/hikikomari-kyuuketsuki-no-monmon-episodio-1/",
                                "title": "Hikikomari Kyuuketsuki no Monmon – Episódio 1",
                                "thumbnail_url": "https://image.tmdb.org/t/p/w500_and_h282_face/ptY78N2W09rEqQtV33JB2pGOsiS.jpg"
                            },
                            {
                                "url": "/episodio/gundam-build-metaverse-episodio-1/",
                                "title": "Gundam Build Metaverse – Episódio 1",
                                "thumbnail_url": "https://image.tmdb.org/t/p/w500_and_h282_face/rWVG7nJTwLtmD5SJNJuckm7HvSF.jpg"
                            },
                            {
                                "url": "/episodio/saihate-no-paladin-2-episodio-1/",
                                "title": "Saihate no Paladin 2 – Episódio 1",
                                "thumbnail_url": "https://image.tmdb.org/t/p/w500_and_h282_face/jY9HGhFJEEsHUeVC2mc8dLaeBLQ.jpg"
                            },
                            {
                                "url": "/episodio/megumi-no-daigo-kyuukoku-no-orange-episodio-2/",
                                "title": "Megumi no Daigo: Kyuukoku no Orange – Episódio 2",
                                "thumbnail_url": "https://image.tmdb.org/t/p/w500_and_h282_face/8fhse3xUv69cZAz1cNWqS2BNLDx.jpg"
                            },
                            {
                                "url": "/episodio/kanojo-mo-kanojo-2-episodio-1/",
                                "title": "Kanojo mo Kanojo 2 – Episódio 1",
                                "thumbnail_url": "https://image.tmdb.org/t/p/w500_and_h282_face/pSizjzRbJTuy2d54al9FKVlelo7.jpg"
                            },
                            {
                                "url": "/episodio/hametsu-no-oukoku-episodio-1/",
                                "title": "Hametsu no Oukoku – Episódio 1",
                                "thumbnail_url": "https://image.tmdb.org/t/p/w500_and_h282_face/iiLkmst7BEKdiodHL7ZRVixyuAR.jpg"
                            },
                            {
                                "url": "/episodio/arknights-fuyukomori-kaerimichi-episodio-1/",
                                "title": "Arknights: Fuyukomori Kaerimichi – Episódio 1",
                                "thumbnail_url": "https://image.tmdb.org/t/p/w500_and_h282_face/mFqt0RPHnohCPhYYJf4Ah0qNgwM.jpg"
                            },
                            {
                                "url": "/episodio/nanatsu-no-maken-ga-shihai-suru-episodio-14/",
                                "title": "Nanatsu no Maken ga Shihai suru – Episódio 14",
                                "thumbnail_url": "https://image.tmdb.org/t/p/w500_and_h282_face/epLIrOUOCDEdWGFw7lxMdLlCT9C.jpg"
                            },
                            {
                                "url": "/episodio/let-me-check-the-walkthrough-first-episodio-1/",
                                "title": "Let Me Check the Walkthrough First – Episódio 1",
                                "thumbnail_url": "https://image.tmdb.org/t/p/w500_and_h282_face/5qi5Qlx9Ayt9HD50EBTtW7uJity.jpg"
                            },
                            {
                                "url": "/episodio/sousou-no-frieren-episodio-5/",
                                "title": "Sousou no Frieren – Episódio 5",
                                "thumbnail_url": "https://image.tmdb.org/t/p/w500_and_h282_face/gI8xcR6tT8beCGbxXFewOuNAVpM.jpg"
                            },
                            {
                                "url": "/episodio/keikenzumi-na-kimi-to-keiken-zero-na-ore-ga-otsukiai-suru-hanashi-episodio-1/",
                                "title": "Keikenzumi na Kimi to, Keiken Zero na Ore ga, Otsukiai suru Hanashi. – Episódio 1",
                                "thumbnail_url": "https://image.tmdb.org/t/p/w500_and_h282_face/5jUdu5VBCMInpwOWi9V52wokSvA.jpg"
                            },
                            {
                                "url": "/episodio/goblin-slayer-2-episodio-1/",
                                "title": "Goblin Slayer 2 – Episódio 1",
                                "thumbnail_url": "https://image.tmdb.org/t/p/w500_and_h282_face/neVAFOKTDpzBeZmrdchiy3CKaqJ.jpg"
                            },
                            {
                                "url": "/episodio/tate-no-yuusha-no-nariagari-3-episodio-1/",
                                "title": "Tate no Yuusha no Nariagari 3 – Episódio 1",
                                "thumbnail_url": "https://image.tmdb.org/t/p/w500_and_h282_face/A9GJMKh2XF9qh9Cxy85gqfpcboi.jpg"
                            },
                            {
                                "url": "/episodio/agate-episodio-15/",
                                "title": "Agate – Episódio 15",
                                "thumbnail_url": "https://image.tmdb.org/t/p/w500_and_h282_face/i1eejeMBkC7uOs2BkKmGWx960R1.jpg"
                            },
                            {
                                "url": "/episodio/rurouni-kenshin-meiji-kenkaku-romantan-2023-episodio-14/",
                                "title": "Rurouni Kenshin: Meiji Kenkaku Romantan (2023) – Episódio 14",
                                "thumbnail_url": "https://image.tmdb.org/t/p/w500_and_h282_face/kMBotf6AVkDnXQOG9ue8GgNabVn.jpg"
                            }
                        ],
                        "hasNextPage": true
                    }
                ],
                "passed": true
            },
            "search": {
                "result": [
                    {
                        "animes": [
                            {
                                "url": "/animes/dr-stone-new-world-part-2/",
                                "title": "Dr. Stone: New World Part 2",
                                "thumbnail_url": "https://image.tmdb.org/t/p/w92/yXwqvG4IN8hzTXQsCD8b8tZ1Ihc.jpg"
                            },
                            {
                                "url": "/animes/world-dai-star/",
                                "title": "World Dai Star",
                                "thumbnail_url": "https://image.tmdb.org/t/p/w92/z3UH88P0heWiJwQ4pHqOsMKUDBH.jpg"
                            },
                            {
                                "url": "/animes/sword-art-online-alicization-war-of-underworld-2/",
                                "title": "Sword Art Online: Alicization – War of Underworld 2",
                                "thumbnail_url": "https://image.tmdb.org/t/p/w92/aaa62CnA8wJLkGu0KHhg8TKxSPq.jpg"
                            },
                            {
                                "url": "/animes/sword-art-online-alicization-war-of-underworld/",
                                "title": "Sword Art Online: Alicization – War of Underworld",
                                "thumbnail_url": "https://image.tmdb.org/t/p/w92/hcYRMCTwIe3aOveEBSPwB2QCIAy.jpg"
                            },
                            {
                                "url": "/animes/dr-stone-new-world/",
                                "title": "Dr. Stone: New World",
                                "thumbnail_url": "https://image.tmdb.org/t/p/w92/3mhFxFzTF0faJwPM0937qTxYHeU.jpg"
                            },
                            {
                                "url": "/animes/rougo-ni-sonaete-isekai-de-8-manmai-no-kinka-wo-tamemasu-dublado/",
                                "title": "Rougo ni Sonaete Isekai de 8-manmai no Kinka wo Tamemasu Dublado",
                                "thumbnail_url": "https://image.tmdb.org/t/p/w92/eW7WipQUnl4zFEqGyoZxDvhgMYK.jpg"
                            },
                            {
                                "url": "/animes/maou-evelogia-ni-mi-wo-sasage-yo/",
                                "title": "Maou Evelogia ni Mi wo Sasage yo",
                                "thumbnail_url": "https://image.tmdb.org/t/p/w92/6Juf2mClD4JpfLVU2YDjLKzFd9E.jpg"
                            },
                            {
                                "url": "/animes/tensei-kizoku-no-isekai-boukenroku-jichou-wo-shiranai-kamigami-no-shito/",
                                "title": "Tensei Kizoku no Isekai Boukenroku: Jichou wo Shiranai Kamigami no Shito",
                                "thumbnail_url": "https://image.tmdb.org/t/p/w92/gZ1BLVWgpAASudNZymVqaaVOT4d.jpg"
                            },
                            {
                                "url": "/animes/kaminaki-sekai-no-kamisama-katsudou/",
                                "title": "Kaminaki Sekai no Kamisama Katsudou",
                                "thumbnail_url": "https://image.tmdb.org/t/p/w92/uTb2twGxJuJN0qdcz3yQQfIHOrN.jpg"
                            },
                            {
                                "url": "/animes/isekai-shoukan-wa-nidome-desu/",
                                "title": "Isekai Shoukan wa Nidome desu",
                                "thumbnail_url": "https://image.tmdb.org/t/p/w92/sAI7DYEuM9mdtZWJiK7YFQcCn0b.jpg"
                            },
                            {
                                "url": "/animes/isekai-de-cheat-skill-wo-te-ni-shita-ore-wa-genjitsu-sekai-wo-mo-musou-suru-level-up-wa-jinsei-wo-kaeta/",
                                "title": "Isekai de Cheat Skill wo Te ni Shita Ore wa, Genjitsu Sekai wo mo Musou Suru: Level Up wa Jinsei wo Kaeta",
                                "thumbnail_url": "https://image.tmdb.org/t/p/w92/50OsbGp6AWw4za2aAM82vKburcg.jpg"
                            },
                            {
                                "url": "/animes/rezero-kara-hajimeru-isekai-seikatsu-2-part-2/",
                                "title": "Re:Zero kara Hajimeru Isekai Seikatsu 2 Part 2",
                                "thumbnail_url": "https://image.tmdb.org/t/p/w92/lktlVRIHEwS3QkgEb1v3uvpTDvp.jpg"
                            },
                            {
                                "url": "/animes/rezero-kara-hajimeru-isekai-seikatsu-2/",
                                "title": "Re:Zero kara Hajimeru Isekai Seikatsu 2",
                                "thumbnail_url": "https://image.tmdb.org/t/p/w92/48mHsftoaWKFdmQMUkO8EYxPNl7.jpg"
                            },
                            {
                                "url": "/animes/rezero-kara-hajimeru-isekai-seikatsu/",
                                "title": "Re:Zero kara Hajimeru Isekai Seikatsu",
                                "thumbnail_url": "https://image.tmdb.org/t/p/w92/aBArXqZA6zuNV1mwBH5UP8aiQoP.jpg"
                            }
                        ],
                        "hasNextPage": false
                    }
                ],
                "passed": true
            },
            "details": {
                "result": {
                    "url": "/animes/hametsu-no-oukoku/",
                    "title": "Hametsu no Oukoku",
                    "description": "As bruxas, num passado distante, abençoaram a raça humana com sabedoria e paz… Porém, a Expansão de Engrenagens do Império Redia trouxe consigo uma cultura científica que superou em muito a magia, e as bruxas passaram a ser vistas como inimigas que impediam o progresso da civilização… Assim começaram as caças às bruxas. Um humano chamado Adonis, que foi criado por uma bruxa chamada Chloe, jura vingança contra a raça humana que tirou sua amada mentora! Que salvação pode ser encontrada no fim de um banho de sangue alimentado por completo desespero?\n\nTítulo original: はめつのおうこく\nTemporadas: 1\nEpisódios: 1",
                    "genre": "Ação, Drama, Fantasia, Gore, Shounen",
                    "thumbnail_url": "https://image.tmdb.org/t/p/w185/j7W5SOtsx6giPtvubEXqWWzKxDL.jpg",
                    "initialized": true
                },
                "passed": true
            },
            "episodes": {
                "result": [
                    {
                        "url": "/episodio/hametsu-no-oukoku-episodio-1/",
                        "name": "Episódio 1",
                        "episode_number": 1.0
                    }
                ],
                "passed": true
            },
            "videos": {
                "result": [
                    {
                        "url": "https://be6721.rcr72.waw04.cdn112.com/hls2/01/04749/uvxika936t83_h/index-v1-a1.m3u8?t=gzMGDPEM63YII5LJcq4zfNLHYmxHKZ4vi-8VeQlpyQo&s=1696788446&e=43200&f=23746075&srv=22&asn=10310&sp=2000",
                        "quality": "Filemoon - 720p",
                        "videoUrl": "https://be6721.rcr72.waw04.cdn112.com/hls2/01/04749/uvxika936t83_h/index-v1-a1.m3u8?t=gzMGDPEM63YII5LJcq4zfNLHYmxHKZ4vi-8VeQlpyQo&s=1696788446&e=43200&f=23746075&srv=22&asn=10310&sp=2000",
                        "headers": {
                            "Referer": "https://filemoon.sx/e/s4rwunqfyrhx?poster=https://image.tmdb.org/t/p/w1280/iiLkmst7BEKdiodHL7ZRVixyuAR.jpg",
                            "Origin": "https://filemoon.sx"
                        }
                    },
                    {
                        "url": "https://wht.nuplink.net/pool/pub/e2/01/56/84c5840fc700180850b2145297e20156/382157935?token=3b66d42d69525929c6f161c204a0157a&ts=1696785896&ht=video/mp4",
                        "quality": "Player - 720p",
                        "videoUrl": "https://wht.nuplink.net/pool/pub/e2/01/56/84c5840fc700180850b2145297e20156/382157935?token=3b66d42d69525929c6f161c204a0157a&ts=1696785896&ht=video/mp4"
                    },
                    {
                        "url": "https://s-delivery35.mxdcontent.net/v/d1b884e9e65c5ab073472ab952898c11.mp4?s=v9JSItb3afMChUJ2gNi_dg&e=1696810056&_t=1696790787",
                        "quality": "MixDrop",
                        "videoUrl": "https://s-delivery35.mxdcontent.net/v/d1b884e9e65c5ab073472ab952898c11.mp4?s=v9JSItb3afMChUJ2gNi_dg&e=1696810056&_t=1696790787",
                        "headers": {
                            "Referer": "https://mixdrop.co/"
                        },
                        "subtitleTracks": [
                            {
                                "url": "",
                                "lang": "sub"
                            }
                        ]
                    },
                    {
                        "url": "https://streamtape.com/get_video?id=9pwwxl0BQpTaqqq&expires=1696858446&ip=F0qQKRWQE19XKxR&token=ZXwZLoqmnTCA",
                        "quality": "StreamTape",
                        "videoUrl": "https://streamtape.com/get_video?id=9pwwxl0BQpTaqqq&expires=1696858446&ip=F0qQKRWQE19XKxR&token=ZXwZLoqmnTCA"
                    }
                ],
                "passed": true
            }
        }
    }
]