[
    {
        "name": "AnimePlayer",
        "results": {
            "popular": {
                "result": [
                    {
                        "animes": [
                            {
                                "url": "/animes/clarencio-o-otimista/",
                                "title": "Clarêncio, O Otimista",
                                "thumbnail_url": "https://animeplayer.com.br/wp-content/uploads/2021/02/qZkAyOlDAxHtQreQE4ZzGfrSQl8-185x278.jpg"
                            },
                            {
                                "url": "/animes/o-incrivel-mundo-de-gumball/",
                                "title": "O Incrível Mundo de Gumball",
                                "thumbnail_url": "https://animeplayer.com.br/wp-content/uploads/2021/01/mTc0xLkcDdV2R0G8Y6H3T0mAyxy-185x278.jpg"
                            },
                            {
                                "url": "/animes/apenas-um-show/",
                                "title": "Apenas Um Show",
                                "thumbnail_url": "https://animeplayer.com.br/wp-content/uploads/2021/02/sTvXT5aXXD6S8QWqnbDnkMX1DCD-185x278.jpg"
                            },
                            {
                                "url": "/animes/hora-de-aventura-dublado/",
                                "title": "Hora de Aventura Dublado",
                                "thumbnail_url": "https://animeplayer.com.br/wp-content/uploads/2023/07/422873-185x278.webp"
                            }
                        ],
                        "hasNextPage": false
                    }
                ],
                "passed": true
            },
            "latest": {
                "result": [
                    {
                        "animes": [
                            {
                                "url": "/episodios/kowaremono-risa-the-animation-1x2/",
                                "title": "Kowaremono: Risa The Animation Episódio 2",
                                "thumbnail_url": "https://animeplayer.com.br/wp-content/uploads/2023/07/dnU6CqUh4HnkW4CYnrHP7ZUvXTq-300x170-1.jpg"
                            },
                            {
                                "url": "/episodios/kowaremono-risa-the-animation-1x1/",
                                "title": "Kowaremono: Risa The Animation Episódio 1",
                                "thumbnail_url": "https://animeplayer.com.br/wp-content/uploads/2023/07/3mk71V1UgRezim3fcuYpLrLdvrg-300x170-1.jpg"
                            },
                            {
                                "url": "/episodios/07-ghost-1x25/",
                                "title": "07 Ghost Episódio 25",
                                "thumbnail_url": "https://animeplayer.com.br/wp-content/uploads/2023/07/ipcBGNalUhomb1mkqZtYBihbJ9T-300x170.jpg"
                            },
                            {
                                "url": "/episodios/07-ghost-1x24/",
                                "title": "07 Ghost Episódio 24",
                                "thumbnail_url": "https://animeplayer.com.br/wp-content/uploads/2023/07/gDySb3f7SZAebPRDmVXvDHX1oCX-300x170.jpg"
                            },
                            {
                                "url": "/episodios/07-ghost-1x23/",
                                "title": "07 Ghost Episódio 23",
                                "thumbnail_url": "https://animeplayer.com.br/wp-content/uploads/2023/07/lyyHCsjMj5bl05CLLT7kc7aZB9o-300x170.jpg"
                            },
                            {
                                "url": "/episodios/07-ghost-1x22/",
                                "title": "07 Ghost Episódio 22",
                                "thumbnail_url": "https://animeplayer.com.br/wp-content/uploads/2023/07/a31EKFSAtlp3RmcSScOLb04Rqbu-300x170.jpg"
                            },
                            {
                                "url": "/episodios/07-ghost-1x21/",
                                "title": "07 Ghost Episódio 21",
                                "thumbnail_url": "https://animeplayer.com.br/wp-content/uploads/2023/07/2zRUerxN84WcRRkwzowFInS8CQk-300x170.jpg"
                            },
                            {
                                "url": "/episodios/07-ghost-1x20/",
                                "title": "07 Ghost Episódio 20",
                                "thumbnail_url": "https://animeplayer.com.br/wp-content/uploads/2023/07/mg7bP7HRuGJ47fJ1cXFRvibihaS-300x170.jpg"
                            },
                            {
                                "url": "/episodios/07-ghost-1x19/",
                                "title": "07 Ghost Episódio 19",
                                "thumbnail_url": "https://animeplayer.com.br/wp-content/uploads/2023/07/7t1xrhnAiNMMW4X2YG3i2RdtGv-300x170.jpg"
                            },
                            {
                                "url": "/episodios/07-ghost-1x18/",
                                "title": "07 Ghost Episódio 18",
                                "thumbnail_url": "https://animeplayer.com.br/wp-content/uploads/2023/07/sty0un0czbh6NbF2epSmFZ7rWo7-300x170.jpg"
                            },
                            {
                                "url": "/episodios/07-ghost-1x17/",
                                "title": "07 Ghost Episódio 17",
                                "thumbnail_url": "https://animeplayer.com.br/wp-content/uploads/2023/07/wFlPAx6yndOc1nkCuURra3089ak-300x170.jpg"
                            },
                            {
                                "url": "/episodios/07-ghost-1x16/",
                                "title": "07 Ghost Episódio 16",
                                "thumbnail_url": "https://animeplayer.com.br/wp-content/uploads/2023/07/xHo0i7sQfBbfqKbCPmn6ynU2uHN-300x170.jpg"
                            },
                            {
                                "url": "/episodios/07-ghost-1x15/",
                                "title": "07 Ghost Episódio 15",
                                "thumbnail_url": "https://animeplayer.com.br/wp-content/uploads/2023/07/uD0fZ4tW8eBOQGB8Cp85te03Rxe-300x170.jpg"
                            },
                            {
                                "url": "/episodios/07-ghost-1x14/",
                                "title": "07 Ghost Episódio 14",
                                "thumbnail_url": "https://animeplayer.com.br/wp-content/uploads/2023/07/4DJV0q5HxGCvJw9SsQrnmYfOarj-300x170.jpg"
                            },
                            {
                                "url": "/episodios/07-ghost-1x13/",
                                "title": "07 Ghost Episódio 13",
                                "thumbnail_url": "https://animeplayer.com.br/wp-content/uploads/2023/07/iQOeTiQ0JMQ9Um9QnQXYppj5Rys-300x170.jpg"
                            },
                            {
                                "url": "/episodios/07-ghost-1x12/",
                                "title": "07 Ghost Episódio 12",
                                "thumbnail_url": "https://animeplayer.com.br/wp-content/uploads/2023/07/jye33Z5d39FrQ7QleX01LHfPWkX-300x170.jpg"
                            },
                            {
                                "url": "/episodios/07-ghost-1x11/",
                                "title": "07 Ghost Episódio 11",
                                "thumbnail_url": "https://animeplayer.com.br/wp-content/uploads/2023/07/vs2qnC9vcP63svZoefxRQ6tlvZ5-300x170.jpg"
                            },
                            {
                                "url": "/episodios/07-ghost-1x10/",
                                "title": "07 Ghost Episódio 10",
                                "thumbnail_url": "https://animeplayer.com.br/wp-content/uploads/2023/07/bQmNlbM6rRn8xxnq2WFTo7TOxxU-300x170.jpg"
                            },
                            {
                                "url": "/episodios/07-ghost-1x9/",
                                "title": "07 Ghost Episódio 9",
                                "thumbnail_url": "https://animeplayer.com.br/wp-content/uploads/2023/07/iQL2DXYDL0CweDELD2D7RkXJB2x-300x170.jpg"
                            },
                            {
                                "url": "/episodios/07-ghost-1x8/",
                                "title": "07 Ghost Episódio 8",
                                "thumbnail_url": "https://animeplayer.com.br/wp-content/uploads/2023/07/f23qPMA7wRg7JVmBxQnajJQxQWe-300x170.jpg"
                            },
                            {
                                "url": "/episodios/07-ghost-1x7/",
                                "title": "07 Ghost Episódio 7",
                                "thumbnail_url": "https://animeplayer.com.br/wp-content/uploads/2023/07/bjZmlvS9YD6UQU0ek10jBQCtNtW-300x170.jpg"
                            }
                        ],
                        "hasNextPage": true
                    }
                ],
                "passed": true
            },
            "search": {
                "result": [
                    {
                        "animes": [
                            {
                                "url": "/animes/world-conquest-zvezda-plot/",
                                "title": "World Conquest Zvezda Plot",
                                "thumbnail_url": "https://animeplayer.com.br/wp-content/uploads/2023/04/q0VlnKNxqNOgIhzxXDgzpnpftyS-150x150.jpg"
                            },
                            {
                                "url": "/animes/seiken-tsukai-no-world-break/",
                                "title": "Seiken Tsukai no World Break",
                                "thumbnail_url": "https://animeplayer.com.br/wp-content/uploads/2021/04/mZRKfWbdX6i3bHrIxthpQpSYfsh-150x150.jpg"
                            },
                            {
                                "url": "/animes/sd-gundam-world-heroes/",
                                "title": "SD Gundam World Heroes",
                                "thumbnail_url": "https://animeplayer.com.br/wp-content/uploads/2021/04/7erAYO2Uj6aKYO3BkcESbGFEs4t-150x150.jpg"
                            },
                            {
                                "url": "/animes/hetalia-world-stars/",
                                "title": "Hetalia World Stars",
                                "thumbnail_url": "https://animeplayer.com.br/wp-content/uploads/2021/04/cM00L1INzac7WWnCpokxVLVdkEW-150x150.jpg"
                            },
                            {
                                "url": "/animes/musaigen-no-phantom-world/",
                                "title": "Musaigen no Phantom World",
                                "thumbnail_url": "https://animeplayer.com.br/wp-content/uploads/2021/03/ahDdggIiFtQh7jj42XKFbtxl4r-150x150.jpg"
                            },
                            {
                                "url": "/animes/accel-world/",
                                "title": "Accel World",
                                "thumbnail_url": "https://animeplayer.com.br/wp-content/uploads/2021/01/seMPV7akEeACgtVTfOEEpTIxjgt-150x150.jpg"
                            },
                            {
                                "url": "/animes/kino-no-tabi-the-beautiful-world-the-animated-series/",
                                "title": "Kino no Tabi: The Beautiful World – The Animated Series",
                                "thumbnail_url": "https://animeplayer.com.br/wp-content/uploads/2020/10/eLeSz6xkAk6HveEXuxGFcGVffeY-150x150.jpg"
                            },
                            {
                                "url": "/animes/world-destruction/",
                                "title": "World Destruction",
                                "thumbnail_url": "https://animeplayer.com.br/wp-content/uploads/2020/09/kJPO8BfqFIWEvSjBbAmLLVnV6Ku-150x150.jpg"
                            },
                            {
                                "url": "/animes/another-world/",
                                "title": "Another World",
                                "thumbnail_url": "https://animeplayer.com.br/wp-content/uploads/2020/06/cFw0rO72AImFaCkPBvVchm0dLWH-150x150.jpg"
                            },
                            {
                                "url": "/animes/rezero-starting-life-in-another-world/",
                                "title": "Re:ZERO -Starting Life in Another World-",
                                "thumbnail_url": "https://animeplayer.com.br/wp-content/uploads/2020/06/o3m8mtRtyDkitb00AGHgbtoTNYh-150x150.jpg"
                            },
                            {
                                "url": "/animes/hack-liminality/",
                                "title": ".hack//Liminality",
                                "thumbnail_url": "https://animeplayer.com.br/wp-content/uploads/2023/07/hGidbV6INqbGoQ5lxGjBmnOj4r0-150x150.jpg"
                            },
                            {
                                "url": "/animes/sushi-police/",
                                "title": "Sushi Police",
                                "thumbnail_url": "https://animeplayer.com.br/wp-content/uploads/2023/06/vSYyiifMe9k0wP2vnf0WT2O4oNE-150x150.jpg"
                            },
                            {
                                "url": "/animes/re-zero-kara-hajimeru-isekai-seikatsu-shin-henshuu-ban/",
                                "title": "Re Zero Kara Hajimeru Isekai Seikatsu – Shin Henshuu-ban",
                                "thumbnail_url": "https://animeplayer.com.br/wp-content/uploads/2023/01/kFUsNsNeW5YyCosmvvSqtqFcWVY-150x150.jpg"
                            },
                            {
                                "url": "/animes/leadale-no-daichi-nite/",
                                "title": "Leadale no Daichi nite",
                                "thumbnail_url": "https://animeplayer.com.br/wp-content/uploads/2022/04/oz3xb8ZpPC9SEKneBrJVK3ZinG6-185x278-1-150x150.jpg"
                            },
                            {
                                "url": "/animes/zombieland-saga/",
                                "title": "Zombieland Saga",
                                "thumbnail_url": "https://animeplayer.com.br/wp-content/uploads/2021/04/e4rzeUloRTHGovb46Zobk3TimhL-150x150.jpg"
                            },
                            {
                                "url": "/animes/lance-n-masques/",
                                "title": "Lance N Masques",
                                "thumbnail_url": "https://animeplayer.com.br/wp-content/uploads/2020/10/AghKnbLP54oxREa33OlOkHO3CN3-150x150.jpg"
                            }
                        ],
                        "hasNextPage": false
                    }
                ],
                "passed": true
            },
            "details": {
                "result": {
                    "url": "/animes/clarencio-o-otimista/",
                    "title": "Clarêncio, O Otimista",
                    "description": "Clarêncio é um menino espirituoso que vê coisas boas em tudo, e por isso é um pouco bobo. Seus melhores amigos são Jeff, um menino que têm fobias e não consegue aguentar coisas sujas, e Sumo, um menino com um jeito maluco que sempre está ao lado de Clarêncio. As perspectivas únicas da vida de Clarêncio podem ser divertidas.\n\nTítulo original: Clarence\nTemporadas: 3",
                    "genre": "",
                    "thumbnail_url": "https://animeplayer.com.br/wp-content/uploads/2021/02/qZkAyOlDAxHtQreQE4ZzGfrSQl8-185x278.jpg",
                    "initialized": true
                },
                "passed": true
            },
            "episodes": {
                "result": [
                    {
                        "url": "/episodios/clarencio-o-otimista-1x40/",
                        "name": "Temporada 1 x 40 - ",
                        "date_upload": 1442793600000,
                        "episode_number": 40.0
                    },
                    {
                        "url": "/episodios/clarencio-o-otimista-1x39/",
                        "name": "Temporada 1 x 39 - ",
                        "date_upload": 1444003200000,
                        "episode_number": 39.0
                    }
                ],
                "passed": true
            },
            "videos": {
                "result": [
                    {
                        "url": "https://rr1---sn-p5qs7nsk.googlevideo.com/videoplayback?expire=1690639659&ei=q6zEZKfpHaSG_9EP79SmuAE&ip=20.57.75.187&id=6bfed712a3fd806c&itag=22&source=blogger&mh=9K&mm=31&mn=sn-p5qs7nsk&ms=au&mv=m&mvi=1&pl=16&susc=bl&eaua=eJXtc50IkiE&mime=video/mp4&vprv=1&dur=649.531&lmt=1443050007972847&mt=1690610472&sparams=expire,ei,ip,id,itag,source,susc,eaua,mime,vprv,dur,lmt&sig=AOq0QJ8wRgIhAK7Vf11yjTZTAuTyghkZkvGvIX-_g3OTGXX33YDUD3ObAiEAsH8n92WtVsas5USRRNrBQkdVGBlbOEs1lhc1qWbFyeM%3D&lsparams=mh,mm,mn,ms,mv,mvi,pl&lsig=AG3C_xAwRQIge7cvyMs0pMzFAjBT_TyL5AgZxlP6ZO8FHmgZq6845yUCIQDguKflG51omwLm2-B580dMMYXyP4hEamwvY9SFjyAwTQ%3D%3D",
                        "quality": "720p",
                        "videoUrl": "https://rr1---sn-p5qs7nsk.googlevideo.com/videoplayback?expire=1690639659&ei=q6zEZKfpHaSG_9EP79SmuAE&ip=20.57.75.187&id=6bfed712a3fd806c&itag=22&source=blogger&mh=9K&mm=31&mn=sn-p5qs7nsk&ms=au&mv=m&mvi=1&pl=16&susc=bl&eaua=eJXtc50IkiE&mime=video/mp4&vprv=1&dur=649.531&lmt=1443050007972847&mt=1690610472&sparams=expire,ei,ip,id,itag,source,susc,eaua,mime,vprv,dur,lmt&sig=AOq0QJ8wRgIhAK7Vf11yjTZTAuTyghkZkvGvIX-_g3OTGXX33YDUD3ObAiEAsH8n92WtVsas5USRRNrBQkdVGBlbOEs1lhc1qWbFyeM%3D&lsparams=mh,mm,mn,ms,mv,mvi,pl&lsig=AG3C_xAwRQIge7cvyMs0pMzFAjBT_TyL5AgZxlP6ZO8FHmgZq6845yUCIQDguKflG51omwLm2-B580dMMYXyP4hEamwvY9SFjyAwTQ%3D%3D",
                        "headers": {
                            "User-Agent": "Mozilla/5.0 (X11; Linux x86_64) AppleWebKit/537.36 (KHTML, like Gecko) Chrome/114.0.5733.0 Safari/537.36",
                            "Referer": "https://animeplayer.com.br"
                        }
                    },
                    {
                        "url": "https://rr1---sn-p5qs7nsk.googlevideo.com/videoplayback?expire=1690639659&ei=q6zEZKfpHaSG_9EP79SmuAE&ip=20.57.75.187&id=6bfed712a3fd806c&itag=18&source=blogger&mh=9K&mm=31&mn=sn-p5qs7nsk&ms=au&mv=m&mvi=1&pl=16&susc=bl&eaua=eJXtc50IkiE&mime=video/mp4&vprv=1&dur=649.531&lmt=1443049925501013&mt=1690610472&sparams=expire,ei,ip,id,itag,source,susc,eaua,mime,vprv,dur,lmt&sig=AOq0QJ8wRQIhAOUf1jpa3soleaCe21B72V4uwqIp9d38hEe9vgryX1uCAiBcpztZ4fW4hBwznf5saUfh5xKGd6id-E5M0sIJBnz7_Q%3D%3D&lsparams=mh,mm,mn,ms,mv,mvi,pl&lsig=AG3C_xAwRgIhAL4VSh459EHmEnvIuAz-ng-Xil5lxRl22F4_s3mGiZlvAiEAqf1ILewP7LbFdBWS0djK6wFYV7aE6TFTysPVcvcr1eg%3D",
                        "quality": "360p",
                        "videoUrl": "https://rr1---sn-p5qs7nsk.googlevideo.com/videoplayback?expire=1690639659&ei=q6zEZKfpHaSG_9EP79SmuAE&ip=20.57.75.187&id=6bfed712a3fd806c&itag=18&source=blogger&mh=9K&mm=31&mn=sn-p5qs7nsk&ms=au&mv=m&mvi=1&pl=16&susc=bl&eaua=eJXtc50IkiE&mime=video/mp4&vprv=1&dur=649.531&lmt=1443049925501013&mt=1690610472&sparams=expire,ei,ip,id,itag,source,susc,eaua,mime,vprv,dur,lmt&sig=AOq0QJ8wRQIhAOUf1jpa3soleaCe21B72V4uwqIp9d38hEe9vgryX1uCAiBcpztZ4fW4hBwznf5saUfh5xKGd6id-E5M0sIJBnz7_Q%3D%3D&lsparams=mh,mm,mn,ms,mv,mvi,pl&lsig=AG3C_xAwRgIhAL4VSh459EHmEnvIuAz-ng-Xil5lxRl22F4_s3mGiZlvAiEAqf1ILewP7LbFdBWS0djK6wFYV7aE6TFTysPVcvcr1eg%3D",
                        "headers": {
                            "User-Agent": "Mozilla/5.0 (X11; Linux x86_64) AppleWebKit/537.36 (KHTML, like Gecko) Chrome/114.0.5733.0 Safari/537.36",
                            "Referer": "https://animeplayer.com.br"
                        }
                    }
                ],
                "passed": true
            }
        }
    }
]