[
    {
        "name": "Cinemathek (DE)",
        "results": {
            "popular": {
                "result": [
                    {
                        "animes": [
                            {
                                "url": "/filme/bittersuesse-schokolade/",
                                "title": "Bittersüße Schokolade",
                                "thumbnail_url": "https://cinemathek.net/wp-content/uploads/2023/12/iCafviaifoCKvvy0zhX01nWZZh9-185x278.jpg"
                            },
                            {
                                "url": "/filme/countdown-to-zero/",
                                "title": "Countdown to Zero",
                                "thumbnail_url": "https://cinemathek.net/wp-content/uploads/2023/12/lJ8EQ4D0x4iPlBxrKGXGtHTwvt6-185x278.jpg"
                            },
                            {
                                "url": "/filme/thomas-seine-freunde-auf-grosser-reise/",
                                "title": "Thomas & seine Freunde – Auf großer Reise",
                                "thumbnail_url": "https://cinemathek.net/wp-content/uploads/2023/12/uHt6IEDmS6xWxbMWNKqxFEpRMdJ.jpg"
                            },
                            {
                                "url": "/filme/love-field-feld-der-liebe/",
                                "title": "Love Field – Feld der Liebe",
                                "thumbnail_url": "https://cinemathek.net/wp-content/uploads/2023/12/jFVu8HdU2oO5UblZKqgdpUfzBGt-185x278.jpg"
                            },
                            {
                                "url": "/filme/der-geheimbund-von-suppenstadt/",
                                "title": "Der Geheimbund von Suppenstadt",
                                "thumbnail_url": "https://cinemathek.net/wp-content/uploads/2023/12/kfuxn4U9LHo7dTAB7QjgXFqQTp2.jpg"
                            },
                            {
                                "url": "/filme/die-letzte-flut/",
                                "title": "Die letzte Flut",
                                "thumbnail_url": "https://cinemathek.net/wp-content/uploads/2023/12/7UwdJ0EMXirUuNFaohfK023Nuyr-185x278.jpg"
                            },
                            {
                                "url": "/filme/nur-noch-weihnachten-im-kopf/",
                                "title": "Nur noch Weihnachten im Kopf",
                                "thumbnail_url": "https://cinemathek.net/wp-content/uploads/2023/12/dZyhvnyfGRkIwEZ73mkSZ1z73S1-185x278.jpg"
                            },
                            {
                                "url": "/filme/vergeltung-sie-werden-dich-finden/",
                                "title": "Vergeltung – Sie werden dich finden",
                                "thumbnail_url": "https://cinemathek.net/wp-content/uploads/2023/12/wTWAIDL5RGMAuQfT0ox8n8tlDqW-185x278.jpg"
                            },
                            {
                                "url": "/filme/once-upon-a-time-in-anatolia/",
                                "title": "Once Upon a Time in Anatolia",
                                "thumbnail_url": "https://cinemathek.net/wp-content/uploads/2023/12/k1t4aQPHMZju6YcJfWH3e1avyOJ.jpg"
                            },
                            {
                                "url": "/filme/benji-und-das-geheimnis-des-kartografen/",
                                "title": "Benji und das Geheimnis des Kartografen",
                                "thumbnail_url": "https://cinemathek.net/wp-content/uploads/2023/12/wTeKSsDikXsEQ2Uqd08cxACXIuL-185x278.jpg"
                            },
                            {
                                "url": "/filme/der-schrei-der-eule/",
                                "title": "Der Schrei der Eule",
                                "thumbnail_url": "https://cinemathek.net/wp-content/uploads/2023/12/zyJAKZgkKdjWWpw6LzffJiN4ee4-185x278.jpg"
                            },
                            {
                                "url": "/filme/voll-verschleiert/",
                                "title": "Voll verschleiert",
                                "thumbnail_url": "https://cinemathek.net/wp-content/uploads/2023/12/sxM6P85IsJOGVj5uvzMlPHPjgo0-185x278.jpg"
                            },
                            {
                                "url": "/filme/fisch-oder-fleisch/",
                                "title": "Fisch oder Fleisch",
                                "thumbnail_url": "https://cinemathek.net/wp-content/uploads/2023/12/v5pT2PBxrOG92Tswd2lB6MojFbP.jpg"
                            },
                            {
                                "url": "/filme/barbarella/",
                                "title": "Barbarella",
                                "thumbnail_url": "https://cinemathek.net/wp-content/uploads/2023/12/kfaRSR3geV3I65icyHWBBEsE9u-185x278.jpg"
                            },
                            {
                                "url": "/filme/der-mythos/",
                                "title": "Der Mythos",
                                "thumbnail_url": "https://cinemathek.net/wp-content/uploads/2023/12/pqbh3DJrUJbHLNbFNzV345kDNqM-185x278.jpg"
                            },
                            {
                                "url": "/filme/das-weihnachtsglas/",
                                "title": "Das Weihnachtsglas",
                                "thumbnail_url": "https://cinemathek.net/wp-content/uploads/2023/12/4BtAfW8XlDc7FLDiMsXWrihwR14-185x278.jpg"
                            },
                            {
                                "url": "/filme/das-leichenhaus-der-lebenden-toten/",
                                "title": "Das Leichenhaus der lebenden Toten",
                                "thumbnail_url": "https://cinemathek.net/wp-content/uploads/2023/12/rGjkJDq86WQYjDP7usCMnNnKdx9.jpg"
                            },
                            {
                                "url": "/filme/headspace-aliens-im-kopf/",
                                "title": "Headspace – Aliens im Kopf",
                                "thumbnail_url": "https://cinemathek.net/wp-content/uploads/2023/12/iruALxOdzO7HCSVd2jAZdB8zZyX-185x278.jpg"
                            },
                            {
                                "url": "/filme/true-lies-wahre-luegen/",
                                "title": "True Lies – Wahre Lügen",
                                "thumbnail_url": "https://cinemathek.net/wp-content/uploads/2023/12/1oSZuYcWnvHeKOtG3OxftUE0qHc.jpg"
                            },
                            {
                                "url": "/filme/die-oekonomie-der-liebe/",
                                "title": "Die Ökonomie der Liebe",
                                "thumbnail_url": "https://cinemathek.net/wp-content/uploads/2023/12/q82NAPZh6gQP4OQbu0ViF6vCleE-185x278.jpg"
                            },
                            {
                                "url": "/filme/sunny/",
                                "title": "Sunny",
                                "thumbnail_url": "https://cinemathek.net/wp-content/uploads/2023/12/kbY4pTPHFxsjzuwoeyIE3RpYTVh-185x278.jpg"
                            },
                            {
                                "url": "/filme/cradle-of-fear/",
                                "title": "Cradle of Fear",
                                "thumbnail_url": "https://cinemathek.net/wp-content/uploads/2023/12/qYNYAFCBd83fOAWIIiL4nG6L2zq-185x278.jpg"
                            },
                            {
                                "url": "/filme/gleissendes-glueck/",
                                "title": "Gleißendes Glück",
                                "thumbnail_url": "https://cinemathek.net/wp-content/uploads/2023/12/i8coeGJEukKwkHKLHKRiX7zq1Rn-185x278.jpg"
                            },
                            {
                                "url": "/filme/the-blade-das-zerbrochene-schwert/",
                                "title": "The Blade – Das zerbrochene Schwert",
                                "thumbnail_url": "https://cinemathek.net/wp-content/uploads/2023/12/plE2R9yLzGI8rY1DBMeOxooOkRq-185x278.jpg"
                            },
                            {
                                "url": "/filme/transmorphers-2-fall-of-man/",
                                "title": "Transmorphers 2 – Fall of Man",
                                "thumbnail_url": "https://cinemathek.net/wp-content/uploads/2023/12/auxCVPfbahHAurjoGuBpXB64yfs-185x278.jpg"
                            },
                            {
                                "url": "/filme/affaere-in-trinidad/",
                                "title": "Affäre in Trinidad",
                                "thumbnail_url": "https://cinemathek.net/wp-content/uploads/2023/12/mn2AVlL1Qz1XQPNH6MzrbW6QzLP-185x278.jpg"
                            },
                            {
                                "url": "/filme/die-rueckkehr-der-18-bronzekaempfer/",
                                "title": "Die Rückkehr der 18 Bronzekämpfer",
                                "thumbnail_url": "https://cinemathek.net/wp-content/uploads/2023/12/7Z6TCagZOkPvyxWjUtR1IkWfAFo-185x278.jpg"
                            },
                            {
                                "url": "/filme/no-mans-land-tatort-911/",
                                "title": "No Man’s Land – Tatort 911",
                                "thumbnail_url": "https://cinemathek.net/wp-content/uploads/2023/12/uWDzLMzQuhfHMkOMiOjJm2KyHzW-185x278.jpg"
                            },
                            {
                                "url": "/filme/wir-kellerkinder/",
                                "title": "Wir Kellerkinder",
                                "thumbnail_url": "https://cinemathek.net/wp-content/uploads/2023/12/oamo3nbzb0AMZtWciqcr1TunV7f-185x278.jpg"
                            },
                            {
                                "url": "/filme/paranormal-resurrection/",
                                "title": "Paranormal Resurrection",
                                "thumbnail_url": "https://cinemathek.net/wp-content/uploads/2023/12/qXSp8CYKcZj1zMVsezuy922bZHQ-185x278.jpg"
                            }
                        ],
                        "hasNextPage": true
                    }
                ],
                "passed": true
            },
            "latest": {
                "result": [
                    {
                        "animes": [
                            {
                                "url": "/episoden/clarksons-farm-1x1/",
                                "title": "Clarkson’s Farm S1E1",
                                "thumbnail_url": "https://cinemathek.net/wp-content/uploads/2023/12/2MMkx4v5fbfNJCoer9SEzuBDeKv-300x170.jpg"
                            },
                            {
                                "url": "/episoden/clarksons-farm-1x2/",
                                "title": "Clarkson’s Farm S1E2",
                                "thumbnail_url": "https://cinemathek.net/wp-content/uploads/2023/12/72T7EFE57lM5PK6svSyC06eJFXJ-300x170.jpg"
                            },
                            {
                                "url": "/episoden/the-billion-dollar-code-1x1/",
                                "title": "The Billion Dollar Code S1E1",
                                "thumbnail_url": "https://cinemathek.net/wp-content/uploads/2023/12/iOZ86zrlm2sqXEWCpHhLY3Asfjv-300x170.jpg"
                            },
                            {
                                "url": "/episoden/clarksons-farm-1x3/",
                                "title": "Clarkson’s Farm S1E3",
                                "thumbnail_url": "https://cinemathek.net/wp-content/uploads/2023/12/60JOrLQPinDS7Fu4f2bgnToI7hy-300x170.jpg"
                            },
                            {
                                "url": "/episoden/the-billion-dollar-code-1x2/",
                                "title": "The Billion Dollar Code S1E2",
                                "thumbnail_url": "https://cinemathek.net/wp-content/uploads/2023/12/nHvHntiGG5Rt4CB4X1IRWpKFjaT-300x170.jpg"
                            },
                            {
                                "url": "/episoden/the-billion-dollar-code-1x3/",
                                "title": "The Billion Dollar Code S1E3",
                                "thumbnail_url": "https://cinemathek.net/wp-content/uploads/2023/12/4waqG5GHHlbesA6814V3RkSoI5f-300x170.jpg"
                            },
                            {
                                "url": "/episoden/clarksons-farm-1x4/",
                                "title": "Clarkson’s Farm S1E4",
                                "thumbnail_url": "https://cinemathek.net/wp-content/uploads/2023/12/gzHeEEBZ0lH23l714S4K4dBgKex-300x170.jpg"
                            },
                            {
                                "url": "/episoden/the-billion-dollar-code-1x4/",
                                "title": "The Billion Dollar Code S1E4",
                                "thumbnail_url": "https://cinemathek.net/wp-content/uploads/2023/12/60qR5tT7c5DgtozTDkEG8TAnbM4-300x170.jpg"
                            },
                            {
                                "url": "/episoden/clarksons-farm-x-3/",
                                "title": "Clarkson’s Farm S1E6",
                                "thumbnail_url": "https://cinemathek.net/wp-content/themes/dooplay/assets/img/no/dt_backdrop.png"
                            },
                            {
                                "url": "/episoden/clarksons-farm-x-2/",
                                "title": "Clarkson’s Farm S1E5",
                                "thumbnail_url": "https://cinemathek.net/wp-content/themes/dooplay/assets/img/no/dt_backdrop.png"
                            },
                            {
                                "url": "/episoden/clarksons-farm-x/",
                                "title": "Clarkson’s Farm S1E7",
                                "thumbnail_url": "https://cinemathek.net/wp-content/themes/dooplay/assets/img/no/dt_backdrop.png"
                            },
                            {
                                "url": "/episoden/clarksons-farm-1x8/",
                                "title": "Clarkson’s Farm S1E8",
                                "thumbnail_url": "https://cinemathek.net/wp-content/uploads/2023/12/kZoanutNuq03nTx7AcH8YnVnd6s-300x170.jpg"
                            },
                            {
                                "url": "/episoden/clarksons-farm-2x1/",
                                "title": "Clarkson’s Farm S2E1",
                                "thumbnail_url": "https://cinemathek.net/wp-content/uploads/2023/12/5p9Rf4xS6BGmewdllEYmxjHAJUg-300x170.jpg"
                            },
                            {
                                "url": "/episoden/clarksons-farm-2x4/",
                                "title": "Clarkson’s Farm S2E4",
                                "thumbnail_url": "https://cinemathek.net/wp-content/uploads/2023/12/aLF1GmysTfHKscHV2VZDInhrosv-300x170.jpg"
                            },
                            {
                                "url": "/episoden/clarksons-farm-2x3/",
                                "title": "Clarkson’s Farm S2E3",
                                "thumbnail_url": "https://cinemathek.net/wp-content/uploads/2023/12/jVe4lsyTbZkY3ie6HbXhaiFzcOX-300x170.jpg"
                            },
                            {
                                "url": "/episoden/clarksons-farm-2x2/",
                                "title": "Clarkson’s Farm S2E2",
                                "thumbnail_url": "https://cinemathek.net/wp-content/uploads/2023/12/zGXOEZ7KMyZ6Pz3PVOyKHMOczCW-300x170.jpg"
                            },
                            {
                                "url": "/episoden/clarksons-farm-2x6/",
                                "title": "Clarkson’s Farm S2E6",
                                "thumbnail_url": "https://cinemathek.net/wp-content/uploads/2023/12/oObvi5GnDuOro1Nf9RL1rF2cG3j-300x170.jpg"
                            },
                            {
                                "url": "/episoden/kein-friede-den-toten-x-2/",
                                "title": "Kein Friede den Toten S1E3",
                                "thumbnail_url": "https://cinemathek.net/wp-content/themes/dooplay/assets/img/no/dt_backdrop.png"
                            },
                            {
                                "url": "/episoden/kein-friede-den-toten-1x1/",
                                "title": "Kein Friede den Toten S1E1",
                                "thumbnail_url": "https://cinemathek.net/wp-content/uploads/2023/12/4yL9VNX9IxoWXxbvNnv4WNTlGF7-300x170.jpg"
                            },
                            {
                                "url": "/episoden/kein-friede-den-toten-1x5/",
                                "title": "Kein Friede den Toten S1E5",
                                "thumbnail_url": "https://cinemathek.net/wp-content/uploads/2023/12/jUHgiInauwQSOYmgNZemVjylu1S-300x170.jpg"
                            },
                            {
                                "url": "/episoden/clarksons-farm-2x8/",
                                "title": "Clarkson’s Farm S2E8",
                                "thumbnail_url": "https://cinemathek.net/wp-content/uploads/2023/12/8hHongJzVZSwjAWi4kGkMwK01aX-300x170.jpg"
                            },
                            {
                                "url": "/episoden/kein-friede-den-toten-1x2/",
                                "title": "Kein Friede den Toten S1E2",
                                "thumbnail_url": "https://cinemathek.net/wp-content/uploads/2023/12/tajBTqpgonHJpk82jm9I830IWOm-300x170.jpg"
                            },
                            {
                                "url": "/episoden/kein-friede-den-toten-1x7/",
                                "title": "Kein Friede den Toten S1E7",
                                "thumbnail_url": "https://cinemathek.net/wp-content/uploads/2023/12/4LCdnygQ5bXyWrb4aZfz2nL4A5j-300x170.jpg"
                            },
                            {
                                "url": "/episoden/kein-friede-den-toten-1x4/",
                                "title": "Kein Friede den Toten S1E4",
                                "thumbnail_url": "https://cinemathek.net/wp-content/uploads/2023/12/dJE9BCPNOW5Di672mPlMVuuPVNY-300x170.jpg"
                            },
                            {
                                "url": "/episoden/kein-friede-den-toten-x/",
                                "title": "Kein Friede den Toten S1E6",
                                "thumbnail_url": "https://cinemathek.net/wp-content/themes/dooplay/assets/img/no/dt_backdrop.png"
                            },
                            {
                                "url": "/episoden/kein-friede-den-toten-1x8/",
                                "title": "Kein Friede den Toten S1E8",
                                "thumbnail_url": "https://cinemathek.net/wp-content/uploads/2023/12/o2Xf958jMUS7H7ggZLt7qYyGTD-300x170.jpg"
                            },
                            {
                                "url": "/episoden/clarksons-farm-2x7/",
                                "title": "Clarkson’s Farm S2E7",
                                "thumbnail_url": "https://cinemathek.net/wp-content/uploads/2023/12/o8NbAw92BHWg4qtMwktkSGPqrTk-300x170.jpg"
                            },
                            {
                                "url": "/episoden/clarksons-farm-2x5/",
                                "title": "Clarkson’s Farm S2E5",
                                "thumbnail_url": "https://cinemathek.net/wp-content/uploads/2023/12/nxAXVpCAR3OfwtdTXTTthWJWY9C-300x170.jpg"
                            },
                            {
                                "url": "/episoden/the-white-lotus-1x1/",
                                "title": "The White Lotus S1E1",
                                "thumbnail_url": "https://cinemathek.net/wp-content/uploads/2023/12/5AkJFSmfPHQDovs23M84p9FPjqy-300x170.jpg"
                            },
                            {
                                "url": "/episoden/the-white-lotus-2x1/",
                                "title": "The White Lotus S2E1",
                                "thumbnail_url": "https://cinemathek.net/wp-content/uploads/2023/12/jZc5svMVSRjStSWIZ4C4XgukbXr-300x170.jpg"
                            }
                        ],
                        "hasNextPage": true
                    }
                ],
                "passed": true
            },
            "search": {
                "result": [
                    {
                        "animes": [
                            {
                                "url": "/filme/the-relative-worlds/",
                                "title": "The Relative Worlds",
                                "thumbnail_url": "https://cinemathek.net/wp-content/uploads/2023/12/aUdImx08qjCtCOellmdYfdrXcGa-150x150.jpg"
                            },
                            {
                                "url": "/filme/leave-the-world-behind/",
                                "title": "Leave the World Behind",
                                "thumbnail_url": "https://cinemathek.net/wp-content/uploads/2023/12/29rhl1xopxA7JlGVVsf1UHfYPvN.jpg"
                            },
                            {
                                "url": "/filme/uzumaki-out-of-the-world/",
                                "title": "Uzumaki – Out of the World",
                                "thumbnail_url": "https://cinemathek.net/wp-content/uploads/2023/11/kmUAEZ6y3RsRn3Keofwl12VsJp6-150x150.jpg"
                            },
                            {
                                "url": "/filme/underworld-awakening/",
                                "title": "Underworld: Awakening",
                                "thumbnail_url": "https://cinemathek.net/wp-content/uploads/2023/11/4eE17OQUb9ak9Pa8vSoD74b3Jg2-150x150.jpg"
                            },
                            {
                                "url": "/filme/death-note-light-up-the-new-world/",
                                "title": "Death Note – Light Up the New World",
                                "thumbnail_url": "https://cinemathek.net/wp-content/uploads/2023/11/kdqVPMK4ePJZHfDQwgKWvAjbaRI.jpg"
                            },
                            {
                                "url": "/filme/underworld/",
                                "title": "Underworld",
                                "thumbnail_url": "https://cinemathek.net/wp-content/uploads/2023/11/8oRit7Uu2K4jKJJNppOp19d0jR-150x150.jpg"
                            },
                            {
                                "url": "/filme/underworld-evolution/",
                                "title": "Underworld: Evolution",
                                "thumbnail_url": "https://cinemathek.net/wp-content/uploads/2023/11/yT1EDKhCzAumcZeBoAxqm0nY2H8-150x150.jpg"
                            },
                            {
                                "url": "/filme/the-worlds-end/",
                                "title": "The World’s End",
                                "thumbnail_url": "https://cinemathek.net/wp-content/uploads/2023/11/uzEpPdjNrFxTWnwHTDCA7bJ7fl8-150x150.jpg"
                            },
                            {
                                "url": "/filme/between-worlds/",
                                "title": "Between Worlds",
                                "thumbnail_url": "https://cinemathek.net/wp-content/uploads/2023/11/7V25KUnWkf0NP7wtGkbmPjEfYf9-150x150.jpg"
                            },
                            {
                                "url": "/filme/jurassic-world-das-gefallene-koenigreich/",
                                "title": "Jurassic World – Das gefallene Königreich",
                                "thumbnail_url": "https://cinemathek.net/wp-content/uploads/2023/11/gIbpCh7nMvLOMxBmkWC6MeQgVr1-150x150.jpg"
                            },
                            {
                                "url": "/filme/a-world-beyond/",
                                "title": "A World Beyond",
                                "thumbnail_url": "https://cinemathek.net/wp-content/uploads/2023/11/5LoUlpif9jueoHWGTfj96s2bY3r-150x150.jpg"
                            },
                            {
                                "url": "/filme/underworld-blood-wars/",
                                "title": "Underworld: Blood Wars",
                                "thumbnail_url": "https://cinemathek.net/wp-content/uploads/2023/11/rLabgQgkM0YrPBZ3BpfLiwRseQo-150x150.jpg"
                            },
                            {
                                "url": "/filme/world-war-z/",
                                "title": "World War Z",
                                "thumbnail_url": "https://cinemathek.net/wp-content/uploads/2023/11/8FSoyuxvUT2HiomWjWA3qIBjQ6Q-150x150.jpg"
                            },
                            {
                                "url": "/filme/jurassic-world-ein-neues-zeitalter/",
                                "title": "Jurassic World – Ein neues Zeitalter",
                                "thumbnail_url": "https://cinemathek.net/wp-content/uploads/2023/11/lYfWPFEIXdtDuTh5jKfkxptN0eF-150x150.jpg"
                            },
                            {
                                "url": "/filme/hellraiser-viii-hellworld/",
                                "title": "Hellraiser VIII: Hellworld",
                                "thumbnail_url": "https://cinemathek.net/wp-content/uploads/2023/11/baWmMOR040IKcMIB1S1vcrykE1D-150x150.jpg"
                            },
                            {
                                "url": "/filme/jurassic-world/",
                                "title": "Jurassic World",
                                "thumbnail_url": "https://cinemathek.net/wp-content/uploads/2023/11/fryDtXgd6Cf4oqNlNPHas0GWDNM-150x150.jpg"
                            },
                            {
                                "url": "/filme/the-cheetah-girls-one-world/",
                                "title": "The Cheetah Girls: One World",
                                "thumbnail_url": "https://cinemathek.net/wp-content/uploads/2023/11/aIxBQvA3h6WbD3LJtXspWL8GOw3-150x150.jpg"
                            },
                            {
                                "url": "/filme/world-of-the-living-dead/",
                                "title": "World Of The Living Dead",
                                "thumbnail_url": "https://cinemathek.net/wp-content/uploads/2023/11/vX3uVYYG1YMbZijRoaFSXtNuIO2-150x150.jpg"
                            },
                            {
                                "url": "/filme/cagefighter-worlds-collide/",
                                "title": "Cagefighter: Worlds Collide",
                                "thumbnail_url": "https://cinemathek.net/wp-content/uploads/2023/10/96OFYM1mP6UJ0NOXDM2zL3APsnp-150x150.jpg"
                            },
                            {
                                "url": "/filme/underworld-gangster/",
                                "title": "Underworld Gangster",
                                "thumbnail_url": "https://cinemathek.net/wp-content/uploads/2023/10/ahlviMZgR6mq3YpwqusKjF48vTh-150x150.jpg"
                            },
                            {
                                "url": "/filme/dark-world-2-equilibrium-2/",
                                "title": "Dark World 2 – Equilibrium",
                                "thumbnail_url": "https://cinemathek.net/wp-content/uploads/2023/10/fIXSQifW5tGhG1f5uo0Q6MFiuLF-150x150.jpg"
                            },
                            {
                                "url": "/filme/dark-world-2-equilibrium/",
                                "title": "Dark World 2 – Equilibrium",
                                "thumbnail_url": "https://cinemathek.net/wp-content/uploads/2023/10/fIXSQifW5tGhG1f5uo0Q6MFiuLF-150x150.jpg"
                            },
                            {
                                "url": "/filme/new-world-order-the-end-has-come/",
                                "title": "New World Order: The End Has Come",
                                "thumbnail_url": "https://cinemathek.net/wp-content/uploads/2023/10/5z2LMsusjn5dxKXS8aMffwhIEhv-150x150.jpg"
                            },
                            {
                                "url": "/filme/cool-world/",
                                "title": "Cool World",
                                "thumbnail_url": "https://cinemathek.net/wp-content/uploads/2023/10/mqzRUHNtFwmgJCmSnvq3JnX0xgZ-150x150.jpg"
                            },
                            {
                                "url": "/filme/independents-war-of-the-worlds/",
                                "title": "Independents – War of the Worlds",
                                "thumbnail_url": "https://cinemathek.net/wp-content/uploads/2023/10/877hJ0hDJyMJhjqfSpM2nStPcsU-150x150.jpg"
                            },
                            {
                                "url": "/filme/bram-stoker-dark-world/",
                                "title": "Bram Stoker: Dark World",
                                "thumbnail_url": "https://cinemathek.net/wp-content/uploads/2023/10/pR3BgTyexRRYv7hvDAm27LTQyIF-150x150.jpg"
                            },
                            {
                                "url": "/filme/ordinary-world/",
                                "title": "Ordinary World",
                                "thumbnail_url": "https://cinemathek.net/wp-content/uploads/2023/10/mEJGrkLvo34nJDLjmLGIqb3SvPb-150x150.jpg"
                            },
                            {
                                "url": "/filme/goodbye-world/",
                                "title": "Goodbye World",
                                "thumbnail_url": "https://cinemathek.net/wp-content/uploads/2023/10/1WEzts5eapNbxglUSNUXUrs98CR-150x150.jpg"
                            },
                            {
                                "url": "/filme/world-of-the-dead-the-zombie-diaries/",
                                "title": "World of the Dead: The Zombie Diaries",
                                "thumbnail_url": "https://cinemathek.net/wp-content/uploads/2023/10/haiamXypDnpkUHu17PCVlrB1bXY-150x150.jpg"
                            },
                            {
                                "url": "/filme/battlefield-fall-of-the-world/",
                                "title": "Battlefield Fall of The World",
                                "thumbnail_url": "https://cinemathek.net/wp-content/uploads/2023/10/zjXcsX3ASORpBWcfsEbkNUshfcD-150x150.jpg"
                            }
                        ],
                        "hasNextPage": false
                    }
                ],
                "passed": true
            },
            "details": {
                "result": {
                    "url": "/filme/bittersuesse-schokolade/",
                    "title": "Bittersüße Schokolade",
                    "description": "Als Teenager verliebt sich die schöne Tita in Pedro. Doch ihre Mutter Elena hat andere Pläne mit ihrer jüngsten Tochter: Tita soll auf Ehemann und Kinder verzichten, um ihrer Mutter zur Seite zu stehen. Um seiner Geliebten dennoch nahe zu sein heiratet Pedro Titas gefügige Schwester Rosaura. Tita findet trotzdem einen Weg, Pedro ihre Liebe zuteil werden zu lassen…\n\nOriginaltitel: Como agua para chocolate",
                    "genre": "Drama, Liebesfilm",
                    "thumbnail_url": "https://cinemathek.net/wp-content/uploads/2023/12/iCafviaifoCKvvy0zhX01nWZZh9-200x300.jpg",
                    "initialized": true
                },
                "passed": true
            },
            "episodes": {
                "result": [
                    {
                        "url": "/filme/bittersuesse-schokolade/",
                        "name": "Movie",
                        "episode_number": 1.0
                    }
                ],
                "passed": true
            },
            "videos": {
                "result": [
                    {
                        "url": "https://streamtape.com/get_video?id=6oWZO43kevF9GZw&expires=1702733706&ip=G0WsDROZKxSHDN&token=8kddxHhJJZ67",
                        "quality": "StreamTape",
                        "videoUrl": "https://streamtape.com/get_video?id=6oWZO43kevF9GZw&expires=1702733706&ip=G0WsDROZKxSHDN&token=8kddxHhJJZ67"
                    },
                    {
                        "url": "https://nue3mlrqqmp4.sw-cdnstream.com/hls2/01/02513/ivh8ixjdk7an_x/index-v1-a1.m3u8?t=CYEXqeb8ZPPyn76RSrD-Ot7ZKYY4FblrnAasV1l5xZw&s=1702663707&e=129600&f=12567006&srv=prrqsnghwdyf&i=0.4&sp=500&p1=prrqsnghwdyf&p2=prrqsnghwdyf&asn=8075",
                        "quality": "StreamWish - 1040p",
                        "videoUrl": "https://nue3mlrqqmp4.sw-cdnstream.com/hls2/01/02513/ivh8ixjdk7an_x/index-v1-a1.m3u8?t=CYEXqeb8ZPPyn76RSrD-Ot7ZKYY4FblrnAasV1l5xZw&s=1702663707&e=129600&f=12567006&srv=prrqsnghwdyf&i=0.4&sp=500&p1=prrqsnghwdyf&p2=prrqsnghwdyf&asn=8075",
                        "headers": {
                            "User-Agent": "Mozilla/5.0 (X11; Linux x86_64; rv:109.0) Gecko/20100101 Firefox/115.0",
                            "Accept": "*/*",
                            "Origin": "https://streamwish.com",
                            "Referer": "https://streamwish.com/e/ivh8ixjdk7an"
                        }
                    }
                ],
                "passed": true
            }
        }
    }
]